tests/__init__.py
tests/context.py
tests/long_kornreich_parsons.py
tests/test_short_kornreich_parsons.py
alpha_eigen-0.0.1.dist-info/LICENSE
alpha_eigen-0.0.1.dist-info/METADATA
alpha_eigen-0.0.1.dist-info/WHEEL
alpha_eigen-0.0.1.dist-info/top_level.txt
alpha_eigen-0.0.1.dist-info/RECORD
