Metadata-Version: 2.1
Name: alpha-eigen
Version: 0.0.1
Summary: Performs dynamic mode decomposition to find alpha-eigenvalues of time-dependent radiation transport
Home-page: https://github.com/clemekay/alpha-eigen
Author: Kayla Clements
Author-email: clemekay@oregonstate.edu
License: UNKNOWN
Platform: UNKNOWN
Classifier: Programming Language :: Python :: 3
Classifier: License :: OSI Approved :: BSD License
Classifier: Operating System :: OS Independent
Requires-Python: >=3.6
License-File: LICENSE
Requires-Dist: numpy
Requires-Dist: h5py
